esmf_aspect_meta_model_python/__init__.py
esmf_aspect_meta_model_python/base/__init__.py
esmf_aspect_meta_model_python/base/aspect.py
esmf_aspect_meta_model_python/base/base.py
esmf_aspect_meta_model_python/base/bound_definition.py
esmf_aspect_meta_model_python/base/cache_strategy.py
esmf_aspect_meta_model_python/base/characteristics/__init__.py
esmf_aspect_meta_model_python/base/characteristics/characteristic.py
esmf_aspect_meta_model_python/base/characteristics/code.py
esmf_aspect_meta_model_python/base/characteristics/collection/__init__.py
esmf_aspect_meta_model_python/base/characteristics/collection/collection.py
esmf_aspect_meta_model_python/base/characteristics/collection/list.py
esmf_aspect_meta_model_python/base/characteristics/collection/set.py
esmf_aspect_meta_model_python/base/characteristics/collection/sorted_set.py
esmf_aspect_meta_model_python/base/characteristics/collection/time_series.py
esmf_aspect_meta_model_python/base/characteristics/enumeration.py
esmf_aspect_meta_model_python/base/characteristics/quantifiable/__init__.py
esmf_aspect_meta_model_python/base/characteristics/quantifiable/duration.py
esmf_aspect_meta_model_python/base/characteristics/quantifiable/measurement.py
esmf_aspect_meta_model_python/base/characteristics/quantifiable/quantifiable.py
esmf_aspect_meta_model_python/base/characteristics/single_entity.py
esmf_aspect_meta_model_python/base/characteristics/state.py
esmf_aspect_meta_model_python/base/characteristics/structured_value.py
esmf_aspect_meta_model_python/base/characteristics/trait.py
esmf_aspect_meta_model_python/base/contraints/__init__.py
esmf_aspect_meta_model_python/base/contraints/constraint.py
esmf_aspect_meta_model_python/base/contraints/encoding_constraint.py
esmf_aspect_meta_model_python/base/contraints/fixed_point_constraint.py
esmf_aspect_meta_model_python/base/contraints/language_constraint.py
esmf_aspect_meta_model_python/base/contraints/length_constraint.py
test_esmf_loader-0.0.2.dist-info/entry_points.txt
test_esmf_loader-0.0.2.dist-info/METADATA
test_esmf_loader-0.0.2.dist-info/WHEEL
test_esmf_loader-0.0.2.dist-info/RECORD
