Metadata-Version: 2.1
Name: test-esmf-loader
Version: 0.0.2
Summary: Load Aspect Models based on the Semantic Aspect Meta Model
Home-page: https://projects.eclipse.org/projects/dt.esmf
License: MPL-2.0
Keywords: samm,esmf,digital twin,idta,model loader,semantic api,semantics,aspect
Author: Hanna Shalamitskaya
Author-email: external.Hanna.Shalamitskaya@de.bosch.com
Requires-Python: >=3.10,<4.0
Classifier: License :: OSI Approved
Classifier: License :: OSI Approved :: Mozilla Public License 2.0 (MPL 2.0)
Classifier: Programming Language :: Python :: 3
Classifier: Programming Language :: Python :: 3.10
Classifier: Programming Language :: Python :: 3.11
Classifier: Programming Language :: Python :: 3
Classifier: Programming Language :: Python :: 3.10
Requires-Dist: rdflib (>=6.2.0,<7.0.0)
Requires-Dist: requests (>=2.28.1,<3.0.0)
Requires-Dist: tox (>=4.5.2,<5.0.0)
Requires-Dist: zipfile37 (>=0.1.3,<0.2.0)
Project-URL: Documentation, https://eclipse-esmf.github.io/python-sdk-guide/index.html
Project-URL: Repository, https://github.com/bci-oss/esmf-sdk-py-aspect-model-loader
